README.md
setup.cfg
setup.py
Flask_Qedit.egg-info/PKG-INFO
Flask_Qedit.egg-info/SOURCES.txt
Flask_Qedit.egg-info/dependency_links.txt
Flask_Qedit.egg-info/entry_points.txt
Flask_Qedit.egg-info/requires.txt
Flask_Qedit.egg-info/top_level.txt
flask_qedit/__init__.py
flask_qedit/finit.py