Metadata-Version: 1.1
Name: Flask-Qedit
Version: 1.0.7
Summary: Quickly initialize the flask application Edit
Home-page: https://github.com/ysicing/Flask-Qedit
Author: ysicing
Author-email: ops.ysicing@gmail.com
License: LGPLv3
Keywords: flask
Platform: any
Classifier: Development Status :: 3 - Alpha
Classifier: Environment :: Console :: Curses
Classifier: Intended Audience :: Developers
Classifier: License :: OSI Approved :: GNU Lesser General Public License v3 (LGPLv3)
Classifier: Programming Language :: Python :: 2.7
Classifier: Programming Language :: Python :: 3.5
Classifier: Programming Language :: Python :: 3.6
